neddy/__init__.py
neddy/__version__.py
neddy/_basesearch.py
neddy/cl_utils.py
neddy/conesearch.py
neddy/default_settings.yaml
neddy/namesearch.py
neddy/test_settings.yaml
neddy/utKit.py
neddy/commonutils/__init__.py
neddy/commonutils/getpackagepath.py
neddy/resources/package.mplstyle
neddy-0.4.1.dist-info/LICENSE
neddy-0.4.1.dist-info/METADATA
neddy-0.4.1.dist-info/WHEEL
neddy-0.4.1.dist-info/entry_points.txt
neddy-0.4.1.dist-info/top_level.txt
neddy-0.4.1.dist-info/RECORD
