Metadata-Version: 2.1
Name: neddy
Version: 0.4.1
Summary: Query the Nasa Extra-Galactic (NED) database via the command-line and programmatically
Home-page: https://github.com/thespacedoctor/neddy
Download-URL: https://github.com/thespacedoctor/neddy/archive/v0.4.1.zip
Author: David Young
Author-email: davidrobertyoung@gmail.com
License: MIT
Keywords: ned, query, astronomy, conesearch
Classifier: Development Status :: 4 - Beta
Classifier: License :: OSI Approved :: MIT License
Classifier: Programming Language :: Python :: 3.9
Classifier: Topic :: Utilities
License-File: LICENSE
Requires-Dist: pyyaml
Requires-Dist: fundamentals
Requires-Dist: astrocalc
Requires-Dist: eventlet
Requires-Dist: numpy
Requires-Dist: unicodecsv
